keibo_common_utils/__init__.py
keibo_common_utils/aws_utils/__init__.py
keibo_common_utils/aws_utils/s3.py
keibo_common_utils/aws_utils/sns.py
keibo_common_utils/logging_utils/__init__.py
keibo_common_utils/logging_utils/p_logger.py
keibo_common_utils-0.0.8.dist-info/LICENSE
keibo_common_utils-0.0.8.dist-info/METADATA
keibo_common_utils-0.0.8.dist-info/WHEEL
keibo_common_utils-0.0.8.dist-info/top_level.txt
keibo_common_utils-0.0.8.dist-info/RECORD
